tootle/__init__.py
tootle/code_io/__init__.py
tootle/code_io/code_writer.py
tootle/dev_bot/__init__.py
tootle/dev_bot/api_documentation_architect.py
tootle/dev_bot/developer.py
tootle/dev_bot/interface_designer.py
tootle/dev_bot/.autom/api_documentation_architect.json
tootle/dev_bot/.autom/developer.json
tootle/dev_bot/.autom/interface_designer.json
tootle/schema/__init__.py
tootle/schema/common.py
tootle-0.0.1.2.dist-info/LICENSE
tootle-0.0.1.2.dist-info/METADATA
tootle-0.0.1.2.dist-info/WHEEL
tootle-0.0.1.2.dist-info/top_level.txt
tootle-0.0.1.2.dist-info/RECORD
