Metadata-Version: 2.1
Name: tootle
Version: 0.0.1.2
Author: 
Author-email: 
License-File: LICENSE
Requires-Dist: gembox
Requires-Dist: pathlib
Requires-Dist: tenacity
Requires-Dist: langchain
